{
  "animation_name": "BouncingDots",
  "output_name": "Procedural Zen #53",
  "timestamp": "2025-12-29T21:23:21.145112",
  "render_time_seconds": 241.53726920008194,
  "config": {
    "animation": {
      "CIRCLE_CENTER_X": 0.0,
      "CIRCLE_CENTER_Y": 0.0,
      "CIRCLE_CENTER_Z": 0.0,
      "CIRCLE_RADIUS": 3.15,
      "CIRCLE_COLOR": "#C3C3C3",
      "CIRCLE_STROKE_WIDTH": 1.93,
      "DOT_START_X": 0.0,
      "DOT_START_Y": 2.5,
      "DOT_START_Z": 0.0,
      "DOT_RADIUS": 0.2,
      "DOT_COLOR": "YELLOW",
      "GRAVITY_X": 0.0,
      "GRAVITY_Y": -9.8,
      "GRAVITY_Z": 0.0,
      "INITIAL_VELOCITY_X": -2.0,
      "INITIAL_VELOCITY_Y": -4.8,
      "INITIAL_VELOCITY_Z": 0.0,
      "DAMPING": 0.99,
      "SIMULATION_DT": 0.001,
      "MAX_SIMULATION_TIME": 600.0,
      "ENABLE_TRAIL": true,
      "TRAIL_COLOR": "RED",
      "TRAIL_WIDTH": 2.69,
      "TRAIL_OPACITY": 0.44,
      "TRAIL_FADING_TIME": 0.75,
      "SOUND_EFFECT": "clack.wav",
      "USE_GENERATED_SOUND": false,
      "MIN_BOUNCE_SOUND_INTERVAL": 0.05,
      "SAMPLE_RATE": 44100.0,
      "DEBUG": false
    },
    "manim": {
      "PIXEL_WIDTH": 2160.0,
      "PIXEL_HEIGHT": 3840.0,
      "FRAME_RATE": 120.0,
      "RENDERER": "cairo",
      "BACKGROUND_COLOR": "BLACK",
      "BACKGROUND_OPACITY": 1.0,
      "MEDIA_DIR": "outputs",
      "FRAME_WIDTH": 8.0,
      "FRAME_HEIGHT": 14.22,
      "SCENE_NAMES": "Default",
      "DISABLE_CACHING": true,
      "FLUSH_CACHE": true
    },
    "dots": {
      "USE_SINGLE_DOT_DEFAULTS": false,
      "DOTS_JSON": [
        {
          "color": "#9A72AC",
          "radius": 0.2,
          "start_pos": [
            1.56,
            0.11,
            0
          ],
          "initial_velocity": [
            -2.97,
            -4.29,
            0
          ],
          "damping": 0.98
        },
        {
          "color": "#F7A1A3",
          "radius": 0.33,
          "start_pos": [
            -0.03,
            -1.12,
            0
          ],
          "initial_velocity": [
            -6.5,
            -5.71,
            0
          ],
          "damping": 0.96
        },
        {
          "color": "#FF862F",
          "radius": 0.26,
          "start_pos": [
            1.05,
            1.27,
            0
          ],
          "initial_velocity": [
            0.54,
            4.03,
            0
          ],
          "damping": 0.95
        },
        {
          "color": "#888888",
          "radius": 0.29,
          "start_pos": [
            0.38,
            1.41,
            0
          ],
          "initial_velocity": [
            4.63,
            -2.79,
            0
          ],
          "damping": 0.96
        },
        {
          "color": "#F0AC5F",
          "radius": 0.26,
          "start_pos": [
            1.62,
            0.38,
            0
          ],
          "initial_velocity": [
            -2.66,
            -0.24,
            0
          ],
          "damping": 0.97
        },
        {
          "color": "#87C2A5",
          "radius": 0.32,
          "start_pos": [
            -1.94,
            0.64,
            0
          ],
          "initial_velocity": [
            -0.49,
            2.83,
            0
          ],
          "damping": 0.96
        }
      ]
    }
  },
  "youtube": {
    "title": "Procedural Zen #53: Noise into Peace | Multiple Bouncy Dots ASMR #animation #asmr #bounce #clack",
    "schedule": {
      "publish_date": "2026-01-13",
      "publish_time": "12:00"
    }
  }
}